<?xml version="1.0" encoding="ASCII" standalone="yes"?>
<CATALOG>

<ROEIMAGE>
	<FILENAME>/mdata/100315184505.roe</FILENAME>
	<NAME>sequence/datademo.seq</NAME>
	<BITPIX>16</BITPIX>
	<WIDTH>2048</WIDTH>
	<HEIGHT>1024</HEIGHT>
	<DATE>15-03-10</DATE>
	<TIME>18:45:05</TIME>
	<ORIGIN>Montana State University</ORIGIN>
	<INSTRUMENT>MOSES</INSTRUMENT>
	<OBSERVER>MOSES lab</OBSERVER>
	<OBJECT>Sun</OBJECT>
	<DURATION>1000194</DURATION>
	<CHANNELS>123</CHANNELS>
	<CHANNEL_SIZE> ch="0">2097152pix</CHANNEL_SIZE>
	<CHANNEL_SIZE> ch="1">2097152pix</CHANNEL_SIZE>
	<CHANNEL_SIZE> ch="2">2097152pix</CHANNEL_SIZE>
	<CHANNEL_SIZE> ch="3">2097152pix</CHANNEL_SIZE>
</ROEIMAGE>

<ROEIMAGE>
	<FILENAME>/mdata/100315184512.roe</FILENAME>
	<NAME>sequence/datademo.seq</NAME>
	<BITPIX>16</BITPIX>
	<WIDTH>2048</WIDTH>
	<HEIGHT>1024</HEIGHT>
	<DATE>15-03-10</DATE>
	<TIME>18:45:12</TIME>
	<ORIGIN>Montana State University</ORIGIN>
	<INSTRUMENT>MOSES</INSTRUMENT>
	<OBSERVER>MOSES lab</OBSERVER>
	<OBJECT>Sun</OBJECT>
	<DURATION>2000770</DURATION>
	<CHANNELS>123</CHANNELS>
	<CHANNEL_SIZE> ch="0">2097152pix</CHANNEL_SIZE>
	<CHANNEL_SIZE> ch="1">2097152pix</CHANNEL_SIZE>
	<CHANNEL_SIZE> ch="2">2097152pix</CHANNEL_SIZE>
	<CHANNEL_SIZE> ch="3">2097152pix</CHANNEL_SIZE>
</ROEIMAGE>

<ROEIMAGE>
	<FILENAME>/mdata/100315184520.roe</FILENAME>
	<NAME>sequence/datademo.seq</NAME>
	<BITPIX>16</BITPIX>
	<WIDTH>2048</WIDTH>
	<HEIGHT>1024</HEIGHT>
	<DATE>15-03-10</DATE>
	<TIME>18:45:20</TIME>
	<ORIGIN>Montana State University</ORIGIN>
	<INSTRUMENT>MOSES</INSTRUMENT>
	<OBSERVER>MOSES lab</OBSERVER>
	<OBJECT>Sun</OBJECT>
	<DURATION>3000701</DURATION>
	<CHANNELS>123</CHANNELS>
	<CHANNEL_SIZE> ch="0">2097152pix</CHANNEL_SIZE>
	<CHANNEL_SIZE> ch="1">2097152pix</CHANNEL_SIZE>
	<CHANNEL_SIZE> ch="2">2097152pix</CHANNEL_SIZE>
	<CHANNEL_SIZE> ch="3">2097152pix</CHANNEL_SIZE>
</ROEIMAGE>

<ROEIMAGE>
	<FILENAME>/mdata/100315184529.roe</FILENAME>
	<NAME>sequence/datademo.seq</NAME>
	<BITPIX>16</BITPIX>
	<WIDTH>2048</WIDTH>
	<HEIGHT>1024</HEIGHT>
	<DATE>15-03-10</DATE>
	<TIME>18:45:29</TIME>
	<ORIGIN>Montana State University</ORIGIN>
	<INSTRUMENT>MOSES</INSTRUMENT>
	<OBSERVER>MOSES lab</OBSERVER>
	<OBJECT>Sun</OBJECT>
	<DURATION>4000555</DURATION>
	<CHANNELS>123</CHANNELS>
	<CHANNEL_SIZE> ch="0">2097152pix</CHANNEL_SIZE>
	<CHANNEL_SIZE> ch="1">2097152pix</CHANNEL_SIZE>
	<CHANNEL_SIZE> ch="2">2097152pix</CHANNEL_SIZE>
	<CHANNEL_SIZE> ch="3">2097152pix</CHANNEL_SIZE>
</ROEIMAGE>

<ROEIMAGE>
	<FILENAME>/mdata/100315184539.roe</FILENAME>
	<NAME>sequence/datademo.seq</NAME>
	<BITPIX>16</BITPIX>
	<WIDTH>2048</WIDTH>
	<HEIGHT>1024</HEIGHT>
	<DATE>15-03-10</DATE>
	<TIME>18:45:39</TIME>
	<ORIGIN>Montana State University</ORIGIN>
	<INSTRUMENT>MOSES</INSTRUMENT>
	<OBSERVER>MOSES lab</OBSERVER>
	<OBJECT>Sun</OBJECT>
	<DURATION>5000442</DURATION>
	<CHANNELS>123</CHANNELS>
	<CHANNEL_SIZE> ch="0">2097152pix</CHANNEL_SIZE>
	<CHANNEL_SIZE> ch="1">2097152pix</CHANNEL_SIZE>
	<CHANNEL_SIZE> ch="2">2097152pix</CHANNEL_SIZE>
	<CHANNEL_SIZE> ch="3">2097152pix</CHANNEL_SIZE>
</ROEIMAGE>

<ROEIMAGE>
	<FILENAME>/mdata/100315185953.roe</FILENAME>
	<NAME>sequence/datademo.seq</NAME>
	<BITPIX>16</BITPIX>
	<WIDTH>2048</WIDTH>
	<HEIGHT>1024</HEIGHT>
	<DATE>15-03-10</DATE>
	<TIME>18:59:53</TIME>
	<ORIGIN>Montana State University</ORIGIN>
	<INSTRUMENT>MOSES</INSTRUMENT>
	<OBSERVER>MOSES lab</OBSERVER>
	<OBJECT>Sun</OBJECT>
	<DURATION>1000907</DURATION>
	<CHANNELS>123</CHANNELS>
	<CHANNEL_SIZE> ch="0">2097152pix</CHANNEL_SIZE>
	<CHANNEL_SIZE> ch="1">2097152pix</CHANNEL_SIZE>
	<CHANNEL_SIZE> ch="2">2097152pix</CHANNEL_SIZE>
	<CHANNEL_SIZE> ch="3">2097152pix</CHANNEL_SIZE>
</ROEIMAGE>

</CATALOG>
